saintBioutils/__init__.py
saintBioutils/genbank/__init__.py
saintBioutils/genbank/get_genomes.py
saintBioutils/genbank/parse_genomes.py
saintBioutils/misc/__init__.py
saintBioutils/uniprot/__init__.py
saintBioutils/utilities/__init__.py
saintBioutils/utilities/file_io/__init__.py
saintBioutils/utilities/file_io/get_paths.py
saintBioutils/utilities/logger/__init__.py
saintBioutils-0.0.25.dist-info/LICENSE
saintBioutils-0.0.25.dist-info/METADATA
saintBioutils-0.0.25.dist-info/WHEEL
saintBioutils-0.0.25.dist-info/top_level.txt
saintBioutils-0.0.25.dist-info/RECORD
