Metadata-Version: 2.1
Name: saintBioutils
Version: 0.0.25
Summary: A package of utility and miscellaneous functions for using in bioinformaticspipelines, primarily in Python.
Home-page: https://github.com/HobnobMancer/saintBioutils
Author: Emma E. M. Hobbs
Author-email: eemh1@st-andrews.ac.uk
License: MIT
Keywords: bioinforamtics python
Platform: Posix
Platform: MacOS X
Classifier: Development Status :: 4 - Beta
Classifier: Environment :: Console
Classifier: Intended Audience :: Science/Research
Classifier: License :: OSI Approved :: MIT License
Classifier: Natural Language :: English
Classifier: Operating System :: POSIX :: Linux
Classifier: Operating System :: MacOS :: MacOS X
Classifier: Programming Language :: Python :: 3.8
Classifier: Topic :: Scientific/Engineering :: Bio-Informatics
License-File: LICENSE
Requires-Dist: biopython (>=1.76)
Requires-Dist: tqdm
